docchunker/__init__.py
docchunker/chunker.py
docchunker/models/__init__.py
docchunker/models/chunk.py
docchunker/processors/__init__.py
docchunker/processors/base_processor.py
docchunker/processors/document_chunker.py
docchunker/processors/docx_parser.py
docchunker/processors/docx_processor.py
docchunker/processors/pdf_parser.py
docchunker/processors/pdf_processor.py
docchunker/utils/__init__.py
docchunker/utils/io_utils.py
docchunker/utils/text_utils.py
docchunker-0.3.0.dist-info/licenses/LICENSE
docchunker-0.3.0.dist-info/METADATA
docchunker-0.3.0.dist-info/WHEEL
docchunker-0.3.0.dist-info/top_level.txt
docchunker-0.3.0.dist-info/RECORD
