Metadata-Version: 2.4
Name: docchunker
Version: 0.3.0
Summary: A specialized document chunking library for complex DOCX and PDF document structures
Author-email: Vlad Griguta <vlad.griguta@gmail.com>
License: MIT
Project-URL: Homepage, https://github.com/vladGriguta/DocChunker
Project-URL: Bug Tracker, https://github.com/vladGriguta/DocChunker/issues
Classifier: Programming Language :: Python :: 3
Classifier: Programming Language :: Python :: 3.9
Classifier: Programming Language :: Python :: 3.10
Classifier: Programming Language :: Python :: 3.11
Classifier: Programming Language :: Python :: 3.12
Classifier: License :: OSI Approved :: MIT License
Classifier: Operating System :: OS Independent
Classifier: Development Status :: 3 - Alpha
Classifier: Intended Audience :: Developers
Classifier: Topic :: Text Processing :: Markup
Requires-Python: >=3.9
License-File: LICENSE
Requires-Dist: python-docx>=0.8.11
Requires-Dist: pypdf>=3.15.1
Requires-Dist: pymupdf>=1.23.0
Provides-Extra: dev
Requires-Dist: pytest>=7.4.0; extra == "dev"
Requires-Dist: pytest-cov>=4.1.0; extra == "dev"
Requires-Dist: mypy>=1.5.1; extra == "dev"
Requires-Dist: black>=23.9.1; extra == "dev"
Requires-Dist: isort>=5.12.0; extra == "dev"
Requires-Dist: ruff>=0.0.292; extra == "dev"
Requires-Dist: pyyaml>=6.0.2; extra == "dev"
Requires-Dist: notebook>=7.4.0; extra == "dev"
Requires-Dist: langchain>=0.3.0; extra == "dev"
Requires-Dist: langchain-community>=0.3.0; extra == "dev"
Requires-Dist: openai>=1.80.0; extra == "dev"
Requires-Dist: faiss-cpu>=1.11.0; extra == "dev"
Dynamic: license-file
